genesis/__init__.py
genesis/cli.py
genesis/config.py
genesis/model.py
genesis/tokenizer.py
genesis/attention/__init__.py
genesis/attention/base.py
genesis/attention/forgetting.py
genesis/attention/gated_attention.py
genesis/attention/utils.py
genesis/dynamics/__init__.py
genesis/dynamics/ttt.py
genesis/layers/__init__.py
genesis/layers/ffn.py
genesis/layers/mup.py
genesis/layers/norms.py
genesis_llm-2.0.3.dist-info/licenses/LICENSE
genesis_llm-2.0.3.dist-info/METADATA
genesis_llm-2.0.3.dist-info/WHEEL
genesis_llm-2.0.3.dist-info/entry_points.txt
genesis_llm-2.0.3.dist-info/top_level.txt
genesis_llm-2.0.3.dist-info/RECORD
