Metadata-Version: 2.4
Name: genesis-llm
Version: 2.0.3
Summary: Genesis architecture (PyTorch) and utilities for inference/benchmarking.
Author: Guilherme Ferrari Bréscia
License: MIT License
Requires-Python: >=3.9
License-File: LICENSE
Requires-Dist: torch>=2.0.0
Requires-Dist: safetensors>=0.4.0
Requires-Dist: transformers>=4.35.0
Provides-Extra: benchmark
Requires-Dist: lighteval; extra == "benchmark"
Requires-Dist: datasets; extra == "benchmark"
Requires-Dist: tqdm; extra == "benchmark"
Provides-Extra: publish
Requires-Dist: build; extra == "publish"
Requires-Dist: twine; extra == "publish"
Requires-Dist: huggingface_hub<1.0,>=0.34.0; extra == "publish"
Dynamic: license-file
